ament_cmake_gmock/_dummy.cpython-313-x86_64-linux-gnu.so
ros_ament_cmake_gmock-2.7.3.data/data/share/ament_cmake_gmock/local_setup.bash
ros_ament_cmake_gmock-2.7.3.data/data/share/ament_cmake_gmock/local_setup.dsv
ros_ament_cmake_gmock-2.7.3.data/data/share/ament_cmake_gmock/local_setup.sh
ros_ament_cmake_gmock-2.7.3.data/data/share/ament_cmake_gmock/local_setup.zsh
ros_ament_cmake_gmock-2.7.3.data/data/share/ament_cmake_gmock/package.dsv
ros_ament_cmake_gmock-2.7.3.data/data/share/ament_cmake_gmock/package.xml
ros_ament_cmake_gmock-2.7.3.data/data/share/ament_cmake_gmock/cmake/ament_add_gmock.cmake
ros_ament_cmake_gmock-2.7.3.data/data/share/ament_cmake_gmock/cmake/ament_add_gmock_executable.cmake
ros_ament_cmake_gmock-2.7.3.data/data/share/ament_cmake_gmock/cmake/ament_add_gmock_test.cmake
ros_ament_cmake_gmock-2.7.3.data/data/share/ament_cmake_gmock/cmake/ament_cmake_gmock-extras.cmake
ros_ament_cmake_gmock-2.7.3.data/data/share/ament_cmake_gmock/cmake/ament_cmake_gmockConfig-version.cmake
ros_ament_cmake_gmock-2.7.3.data/data/share/ament_cmake_gmock/cmake/ament_cmake_gmockConfig.cmake
ros_ament_cmake_gmock-2.7.3.data/data/share/ament_cmake_gmock/cmake/ament_find_gmock.cmake
ros_ament_cmake_gmock-2.7.3.data/data/share/ament_cmake_gmock/environment/ament_prefix_path.dsv
ros_ament_cmake_gmock-2.7.3.data/data/share/ament_cmake_gmock/environment/ament_prefix_path.sh
ros_ament_cmake_gmock-2.7.3.data/data/share/ament_cmake_gmock/environment/path.dsv
ros_ament_cmake_gmock-2.7.3.data/data/share/ament_cmake_gmock/environment/path.sh
ros_ament_cmake_gmock-2.7.3.data/data/share/ament_index/resource_index/package_run_dependencies/ament_cmake_gmock
ros_ament_cmake_gmock-2.7.3.data/data/share/ament_index/resource_index/packages/ament_cmake_gmock
ros_ament_cmake_gmock-2.7.3.data/data/share/ament_index/resource_index/parent_prefix_path/ament_cmake_gmock
ros_ament_cmake_gmock-2.7.3.dist-info/METADATA
ros_ament_cmake_gmock-2.7.3.dist-info/WHEEL
ros_ament_cmake_gmock-2.7.3.dist-info/top_level.txt
ros_ament_cmake_gmock-2.7.3.dist-info/RECORD
