Metadata-Version: 2.4
Name: ros-ament-cmake-gmock
Version: 2.7.3
Summary: Wheel for the ament_cmake_gmock (ros-ament-cmake-gmock) ROS 2 package.
Dynamic: description
Dynamic: description-content-type
Dynamic: summary
